{"type":{"0":"W","1":"W"},"module":{"0":"setup","1":"setup"},"obj":{"0":"PyTestCommand.initialize_options","1":"PyTestCommand.finalize_options"},"lnum":{"0":96,"1":101},"col":{"0":8,"1":8},"filename":{"0":"setup.py","1":"setup.py"},"symbol":{"0":"attribute-defined-outside-init","1":"attribute-defined-outside-init"},"text":{"0":"Attribute 'pytest_args' defined outside __init__","1":"Attribute 'test_suite' defined outside __init__"},"number":{"0":"W0201","1":"W0201"},"linter":{"0":"pylint","1":"pylint"},"lines_amount":{"0":480,"1":480},"commit":{"0":"37af7fd5de3ed148b8096cfc80e4717fb840bf2c","1":"37af7fd5de3ed148b8096cfc80e4717fb840bf2c"},"repo":{"0":"coala\/coala","1":"coala\/coala"}}