{"type":{"0":"C","1":"C","2":"R","3":"R","4":"R","5":"C","6":"C","7":"C","8":"C"},"module":{"0":"model","1":"reader","2":"reader","3":"reader","4":"reader","5":"seq2seq","6":"seq2seq","7":"seq2seq","8":"server"},"obj":{"0":"Model.eval","1":"padding_seq","2":"read_vocab","3":"SeqReader._init_reader","4":"SeqReader._init_reader","5":"seq2seq","6":"seq2seq","7":"seq2seq","8":"manual_correct_result"},"lnum":{"0":198,"1":12,"2":47,"3":117,"4":118,"5":112,"6":134,"7":170,"8":61},"col":{"0":16,"1":4,"2":9,"3":18,"4":19,"5":7,"6":7,"7":7,"8":4},"filename":{"0":"model.py","1":"reader.py","2":"reader.py","3":"reader.py","4":"reader.py","5":"seq2seq.py","6":"seq2seq.py","7":"seq2seq.py","8":"server.py"},"symbol":{"0":"consider-using-enumerate","1":"consider-using-enumerate","2":"consider-using-with","3":"consider-using-with","4":"consider-using-with","5":"singleton-comparison","6":"singleton-comparison","7":"singleton-comparison","8":"consider-using-enumerate"},"text":{"0":"Consider using enumerate instead of iterating with range and len","1":"Consider using enumerate instead of iterating with range and len","2":"Consider using 'with' for resource-allocating operations","3":"Consider using 'with' for resource-allocating operations","4":"Consider using 'with' for resource-allocating operations","5":"Comparison 'target_seq != None' should be 'target_seq is not None'","6":"Comparison 'target_seq != None' should be 'target_seq is not None'","7":"Comparison 'target_seq != None' should be 'target_seq is not None'","8":"Consider using enumerate instead of iterating with range and len"},"number":{"0":"C0200","1":"C0200","2":"R1732","3":"R1732","4":"R1732","5":"C0121","6":"C0121","7":"C0121","8":"C0200"},"linter":{"0":"pylint","1":"pylint","2":"pylint","3":"pylint","4":"pylint","5":"pylint","6":"pylint","7":"pylint","8":"pylint"},"lines_amount":{"0":239,"1":142,"2":142,"3":142,"4":142,"5":186,"6":186,"7":186,"8":121},"commit":{"0":"460cb8bd4af23f17e6436feab46847a366ef4672","1":"460cb8bd4af23f17e6436feab46847a366ef4672","2":"460cb8bd4af23f17e6436feab46847a366ef4672","3":"460cb8bd4af23f17e6436feab46847a366ef4672","4":"460cb8bd4af23f17e6436feab46847a366ef4672","5":"460cb8bd4af23f17e6436feab46847a366ef4672","6":"460cb8bd4af23f17e6436feab46847a366ef4672","7":"460cb8bd4af23f17e6436feab46847a366ef4672","8":"460cb8bd4af23f17e6436feab46847a366ef4672"},"repo":{"0":"wb14123\/seq2seq-couplet","1":"wb14123\/seq2seq-couplet","2":"wb14123\/seq2seq-couplet","3":"wb14123\/seq2seq-couplet","4":"wb14123\/seq2seq-couplet","5":"wb14123\/seq2seq-couplet","6":"wb14123\/seq2seq-couplet","7":"wb14123\/seq2seq-couplet","8":"wb14123\/seq2seq-couplet"}}